django_utilsds/__init__.py
django_utilsds/admin.py
django_utilsds/apps.py
django_utilsds/models.py
django_utilsds/tests.py
django_utilsds/utils.py
django_utilsds/views.py
django_utilsds/migrations/__init__.py
django_utilsds/templatetags/django_utilsds_tags.py
django_utilsds-0.7.1.dist-info/LICENSE
django_utilsds-0.7.1.dist-info/WHEEL
django_utilsds-0.7.1.dist-info/METADATA
django_utilsds-0.7.1.dist-info/RECORD
