Metadata-Version: 2.1
Name: django-utilsds
Version: 0.7.1
Summary: One of the my demiansoft apps
Author-email: Hyungjin Kim <hj3415@gmail.com>
Classifier: License :: OSI Approved :: MIT License
Requires-Dist: Django >= 4.2.11
Project-URL: Home, https://www.demiansoft.com
